forecast/__init__.py
forecast/cli.py
forecast/forecast.py
forecast-0.1.0.dist-info/DESCRIPTION.rst
forecast-0.1.0.dist-info/METADATA
forecast-0.1.0.dist-info/RECORD
forecast-0.1.0.dist-info/WHEEL
forecast-0.1.0.dist-info/entry_points.txt
forecast-0.1.0.dist-info/metadata.json
forecast-0.1.0.dist-info/top_level.txt
