Metadata-Version: 1.1
Name: forecast
Version: 0.1.0
Summary: Implemetion of Book 'forcasting priceples and practise'
Home-page: https://github.com/BlackPoint-CX/forecast
Author: Alfred Chen
Author-email: chenxiang0815@gmail.com
License: MIT license
Keywords: forecast
Platform: UNKNOWN
Classifier: Development Status :: 2 - Pre-Alpha
Classifier: Intended Audience :: Developers
Classifier: License :: OSI Approved :: MIT License
Classifier: Natural Language :: English
Classifier: Programming Language :: Python :: 2
Classifier: Programming Language :: Python :: 2.6
Classifier: Programming Language :: Python :: 2.7
Classifier: Programming Language :: Python :: 3
Classifier: Programming Language :: Python :: 3.3
Classifier: Programming Language :: Python :: 3.4
Classifier: Programming Language :: Python :: 3.5
